AUTHORS.txt
LICENSE.txt
MANIFEST.in
README.rst
setup.py
NagParser.egg-info/PKG-INFO
NagParser.egg-info/SOURCES.txt
NagParser.egg-info/dependency_links.txt
NagParser.egg-info/requires.txt
NagParser.egg-info/top_level.txt
docs/index.rst
docs/_build/html/_sources/index.txt
nagparser/Nag.py
nagparser/NagCommands.py
nagparser/NagConfig.py
nagparser/NagList.py
nagparser/__init__.py
nagparser/factory.py
nagparser/nicetime.py
nagparser/test/__init__.py
nagparser/test/test_nag_parser.py
nagparser/test/data/test_objects.cache
nagparser/test/data/test_status.dat